README.txt
setup.cfg
setup.py
gpfanova/__init__.py
gpfanova/base.py
gpfanova/dataset.py
gpfanova/fanova.py
gpfanova/interval.py
gpfanova/linalg.py
gpfanova/mean.py
gpfanova/prior.py
gpfanova.egg-info/PKG-INFO
gpfanova.egg-info/SOURCES.txt
gpfanova.egg-info/dependency_links.txt
gpfanova.egg-info/requires.txt
gpfanova.egg-info/top_level.txt
gpfanova/kernel/__init__.py
gpfanova/kernel/add.py
gpfanova/kernel/kernel.c
gpfanova/kernel/rbf.c
gpfanova/kernel/white.py
gpfanova/plot/__init__.py
gpfanova/plot/function.py
gpfanova/plot/hyperparams.py
gpfanova/plot/interaction.py
gpfanova/plot/meta.py
gpfanova/plot/multipleeffect.py
gpfanova/plot/single_effect.py
gpfanova/plot/twoeffect.py
gpfanova/sample/__init__.py
gpfanova/sample/container.py
gpfanova/sample/fixed.py
gpfanova/sample/function.py
gpfanova/sample/gibbs.py
gpfanova/sample/posterior.py
gpfanova/sample/sampler.py
gpfanova/sample/slice.c
gpfanova/sample/transform.py